dj_pydantic_settings/__init__.py
dj_pydantic_settings-0.1.1.dist-info/METADATA
dj_pydantic_settings-0.1.1.dist-info/WHEEL
dj_pydantic_settings-0.1.1.dist-info/RECORD
