Metadata-Version: 2.3
Name: dj-pydantic-settings
Version: 0.1.1
Summary: Add your description here
Author-email: Vova Abdrakhmanov <369565@gmail.com>
Requires-Python: >=3.8
Requires-Dist: dj-database-url>=2.2.0
Requires-Dist: pydantic-settings>=2.5.2
